git_checkpoints/__init__.py
git_checkpoints/cli.py
git_checkpoints-2.0.3.data/data/git-checkpoints
git_checkpoints-2.0.3.data/data/install.sh
git_checkpoints-2.0.3.dist-info/licenses/LICENSE
git_checkpoints-2.0.3.dist-info/METADATA
git_checkpoints-2.0.3.dist-info/WHEEL
git_checkpoints-2.0.3.dist-info/entry_points.txt
git_checkpoints-2.0.3.dist-info/top_level.txt
git_checkpoints-2.0.3.dist-info/RECORD
