Metadata-Version: 2.4
Name: git-checkpoints
Version: 2.0.3
Summary: Zero-config, language-agnostic Git snapshots via tags
Home-page: https://github.com/moussa-m/git-checkpoints
Author: Moussa Mokhtari
Author-email: me@moussamokhtari.com
License: MIT
Project-URL: Bug Reports, https://github.com/moussa-m/git-checkpoints/issues
Project-URL: Source, https://github.com/moussa-m/git-checkpoints
Keywords: git version-control checkpoints snapshots tags backup
Classifier: Development Status :: 5 - Production/Stable
Classifier: Intended Audience :: Developers
Classifier: Topic :: Software Development :: Version Control
Classifier: Topic :: Software Development :: Version Control :: Git
Classifier: Programming Language :: Python :: 3
Classifier: Programming Language :: Python :: 3.6
Classifier: Programming Language :: Python :: 3.7
Classifier: Programming Language :: Python :: 3.8
Classifier: Programming Language :: Python :: 3.9
Classifier: Programming Language :: Python :: 3.10
Classifier: Programming Language :: Python :: 3.11
Classifier: Programming Language :: Python :: 3.12
Classifier: Operating System :: POSIX :: Linux
Classifier: Operating System :: MacOS
Classifier: Operating System :: Unix
Requires-Python: >=3.6
License-File: LICENSE
Dynamic: author
Dynamic: author-email
Dynamic: classifier
Dynamic: description
Dynamic: description-content-type
Dynamic: home-page
Dynamic: keywords
Dynamic: license
Dynamic: license-file
Dynamic: project-url
Dynamic: requires-python
Dynamic: summary
